tiny_data_analytics_tool/Example.py
tiny_data_analytics_tool/Settings.py
tiny_data_analytics_tool/TinyDataAnalyticsTool.py
tiny_data_analytics_tool/__init__.py
TinyDataAnalyticsTool-0.1.0.dist-info/LICENSE
TinyDataAnalyticsTool-0.1.0.dist-info/METADATA
TinyDataAnalyticsTool-0.1.0.dist-info/WHEEL
TinyDataAnalyticsTool-0.1.0.dist-info/top_level.txt
TinyDataAnalyticsTool-0.1.0.dist-info/RECORD
