Metadata-Version: 2.1
Name: TinyDataAnalyticsTool
Version: 0.1.0
Summary: Disclaimer: This is an old Project from when I started learning Python from 2019 (not the best written code)!! A GUI for flexibly organizing Data Analytics related tasks/functions and adding custom User Input Fields if needed.
Home-page: https://github.com/efstratios97/Tiny-Data-Analytics-Tool
Author: Efstratios Pahis
License: MIT
Classifier: Programming Language :: Python :: 3
Classifier: License :: OSI Approved :: MIT License
Classifier: Operating System :: OS Independent
Requires-Python: >=3.6
License-File: LICENSE
Requires-Dist: pandas
Requires-Dist: matplotlib
Requires-Dist: openpyxl
